cartero/__init__.py
cartero/lib.py
cartero-0.1.10.dist-info/METADATA
cartero-0.1.10.dist-info/WHEEL
cartero-0.1.10.dist-info/RECORD
