Metadata-Version: 2.4
Name: cartero
Version: 0.1.10
Summary: Utilidad muy básica para enviar correos electrónicos.
Author-email: Sergio Puche García <serpucga@inf.upv.es>
License: GPL3
Requires-Python: >=3.8
Requires-Dist: logutils-serpucga==0.2.2
Requires-Dist: pydantic>=2.10.6
